{"parent_taxon":"cordylidae","popular_subtaxa":[],"example_member":"","example_member_type":"","taxonomic_rank":"Species","scientific_name":"Ninurta coeruleopunctatus","other_names":[],"description":"","wikipedia_img":"https://upload.wikimedia.org/wikipedia/commons/thumb/7/76/Ninurta_coeruleopunctatus%2C_Nature%27s_Valley.jpg/220px-Ninurta_coeruleopunctatus%2C_Nature%27s_Valley.jpg","wikipedia_page":"https://en.wikipedia.org/wiki/Ninurta_coeruleopunctatus","popular_ancestors":["amniote","tetrapod","animal","life"],"popularity":50,"extinct":false,"name":"blue-spotted girdled lizard"}