{"parent_taxon":"cupressoideae subclade 5","popular_subtaxa":[],"example_member":"","example_member_type":"","taxonomic_rank":"Genus","scientific_name":"","other_names":[],"description":"","wikipedia_img":"https://upload.wikimedia.org/wikipedia/commons/thumb/5/5c/Incense_Cedar_in_Lassen_VNP.jpg/220px-Incense_Cedar_in_Lassen_VNP.jpg","wikipedia_page":"https://en.wikipedia.org/wiki/Calocedrus","popular_ancestors":["conifer","land plant","cellular life","life"],"popularity":55,"extinct":false,"name":"incense cedar"}