{"parent_taxon":"trochozoa","popular_subtaxa":[],"example_member":"","example_member_type":"","taxonomic_rank":"Phylum","scientific_name":"","other_names":["ribbon worms","proboscis worms"],"description":"","wikipedia_img":"https://upload.wikimedia.org/wikipedia/commons/thumb/5/50/Nemertea_Terrestrial_W_Java.png/220px-Nemertea_Terrestrial_W_Java.png","wikipedia_page":"https://en.wikipedia.org/wiki/Nemertea","popular_ancestors":["protostomia","animal","cellular life","life"],"popularity":10,"extinct":false,"name":"nemertea"}