{"parent_taxon":"monocot subclade 3","popular_subtaxa":[],"example_member":"","example_member_type":"","taxonomic_rank":"Order","scientific_name":"","other_names":[],"description":"","wikipedia_img":"https://upload.wikimedia.org/wikipedia/commons/thumb/4/4f/Starr_080917-9948_Freycinetia_arborea.jpg/220px-Starr_080917-9948_Freycinetia_arborea.jpg","wikipedia_page":"https://en.wikipedia.org/wiki/Pandanales","popular_ancestors":["flowering plant","land plant","cellular life","life"],"popularity":10,"extinct":false,"name":"pandanales"}