{"parent_taxon":"trematosauroidea","popular_subtaxa":[],"example_member":"","example_member_type":"","taxonomic_rank":"Genus","scientific_name":"","other_names":[],"description":"","wikipedia_img":"https://upload.wikimedia.org/wikipedia/commons/thumb/1/1e/Trematosaurus1DB.jpg/220px-Trematosaurus1DB.jpg","wikipedia_page":"https://upload.wikimedia.org/wikipedia/commons/thumb/1/1e/Trematosaurus1DB.jpg/330px-Trematosaurus1DB.jpg","popular_ancestors":["amphibian","tetrapod","animal","life"],"popularity":10,"extinct":true,"name":"trematosaurus"}