{
"description":"",
"popularity":10,
"extinct":true,
"name":"Albertonykus",
"parentTaxon":"parvicursorinae subclade 1",
"popularSubtaxa":[],
"exampleMember":"",
"exampleMemberType":"",
"taxonomicRank":"Genus",
"scientificName":"",
"otherNames":[],
"wikipediaImg":"https://upload.wikimedia.org/wikipedia/commons/thumb/7/73/Albertonykus_borealis.jpg/330px-Albertonykus_borealis.jpg",
"wikipediaPage":"https://en.wikipedia.org/wiki/Albertonykus",
"popularAncestors":[
"saurischia",
"dinosaur",
"animal",
"life"
],
"subtaxa":[],
"popularAncestorPops":[
40,
95,
95,
100
],
"popularSubtaxaPops":[],
"popularSubtaxaSameBranch":"",
"additionalSubTaxa":[]
}