{
"description": "",
"popularity": 50,
"extinct": false,
"name": "Amazon bamboo rat",
"parentTaxon": "dactylomyinae",
"popularSubtaxa": [],
"exampleMember": "",
"exampleMemberType": "",
"taxonomicRank": "Species",
"scientificName": "Dactylomys dactylinus",
"otherNames": [],
"wikipediaImg": "https://upload.wikimedia.org/wikipedia/commons/thumb/6/6d/AmazonBambooRat.JPG/220px-AmazonBambooRat.JPG",
"wikipediaPage": "https://en.wikipedia.org/wiki/Amazon_bamboo_rat",
"popularAncestors": [
"rodent",
"mammal",
"animal",
"life"
],
"subtaxa": []
}