{
"description":"",
"popularity":"",
"extinct":false,
"name":"Bubalus",
"parentTaxon":"bovini",
"popularSubtaxa":[
"water buffalo",
"wild water buffalo",
"anoa"
],
"exampleMember":"wild water buffalo",
"exampleMemberType":"Example Member",
"taxonomicRank":"Genus",
"scientificName":"",
"otherNames":[],
"wikipediaImg":"",
"wikipediaPage":"https://en.wikipedia.org/wiki/Bubalus",
"popularAncestors":[
"mammal",
"amniote",
"animal",
"life"
],
"subtaxa":[
"water buffalo",
"wild water buffalo",
"anoa",
"tamaraw"
],
"popularAncestorPops":[
70,
50,
95,
100
],
"popularSubtaxaPops":[
70,
55,
50
],
"popularSubtaxaSameBranch":""
}