{
"description":"",
"popularity":"",
"extinct":true,
"name":"Carcharodontosauridae",
"parentTaxon":"carcharodontosauria",
"popularSubtaxa":[
"giganotosaurus",
"carcharodontosaurus",
"tyrannotitan"
],
"exampleMember":"concavenator",
"exampleMemberType":"Example Member",
"taxonomicRank":"Family",
"scientificName":"",
"otherNames":[],
"wikipediaImg":"",
"wikipediaPage":"https://en.wikipedia.org/wiki/Carcharodontosauridae",
"popularAncestors":[
"saurischia",
"dinosaur",
"animal",
"life"
],
"subtaxa":[
"carcharodontosauridae subclade 1",
"concavenator"
],
"popularAncestorPops":[
40,
95,
95,
100
],
"popularSubtaxaPops":[
50,
40,
30
],
"popularSubtaxaSameBranch":"0,2"
}