{
"description": "",
"popularity": "",
"extinct": false,
"name": "Chelicerata",
"parentTaxon": "arthropod",
"popularSubtaxa": [
"horseshoe crab",
"tick",
"spider"
],
"exampleMember": "eurypterida",
"exampleMemberType": "Early Member",
"taxonomicRank": "Subphylum",
"scientificName": "",
"otherNames": [],
"wikipediaImg": "",
"wikipediaPage": "http://en.wikipedia.org/wiki/Chelicerate",
"popularAncestors": [
"arthropod",
"animal",
"cellular life",
"life"
],
"subtaxa": [
"arachnid",
"merostomata"
]
}