{
"description":"",
"popularity":"",
"extinct":false,
"name":"Crocodilia",
"parentTaxon":"eusuchia subclade 1",
"popularSubtaxa":[
"alligator",
"crocodile",
"gharial"
],
"exampleMember":"allodaposuchus",
"exampleMemberType":"Early Member",
"taxonomicRank":"Order",
"scientificName":"",
"otherNames":[
"Crocodylia"
],
"wikipediaImg":"",
"wikipediaPage":"https://en.wikipedia.org/wiki/Crocodilia",
"popularAncestors":[
"amniote",
"tetrapod",
"animal",
"life"
],
"subtaxa":[
"crocodilia subclade 1",
"gharial"
],
"popularAncestorPops":[
50,
50,
95,
100
],
"popularSubtaxaPops":[
85,
80,
50
],
"popularSubtaxaSameBranch":"0,1"
}