{
"description": "",
"popularity": 30,
"extinct": false,
"name": "Dorcopsis",
"parentTaxon": "macropodinae",
"popularSubtaxa": [],
"exampleMember": "",
"exampleMemberType": "",
"taxonomicRank": "Genus",
"scientificName": "",
"otherNames": [],
"wikipediaImg": "https://upload.wikimedia.org/wikipedia/commons/thumb/1/10/HalmaturusLuctuosusKeulemans.jpg/220px-HalmaturusLuctuosusKeulemans.jpg",
"wikipediaPage": "http://en.wikipedia.org/wiki/Dorcopsis_%28genus%29",
"popularAncestors": [
"marsupial",
"mammal",
"animal",
"life"
],
"subtaxa": []
}