{
"description":"",
"popularity":"",
"extinct":true,
"name":"Elmisaurinae",
"parentTaxon":"caenagnathidae subclade 3",
"popularSubtaxa":[
"caenagnathasia",
"elmisaurus",
"apatoraptor"
],
"exampleMember":"caenagnathasia",
"exampleMemberType":"Example Member",
"taxonomicRank":"",
"scientificName":"",
"otherNames":[],
"wikipediaImg":"",
"wikipediaPage":"https://en.wikipedia.org/wiki/Caenagnathidae",
"popularAncestors":[
"saurischia",
"dinosaur",
"animal",
"life"
],
"subtaxa":[
"caenagnathasia",
"elmisaurinae subclade 1"
],
"popularAncestorPops":[
40,
95,
95,
100
],
"popularSubtaxaPops":[
10,
20,
10
],
"needs_wiki_img_checked":true
}