{
"description": "",
"popularity": "",
"extinct": false,
"name": "Eumysopinae",
"parentTaxon": "echimyidae",
"popularSubtaxa": [
"armored rat",
"ferreira's spiny tree rat"
],
"exampleMember": "armored rat",
"exampleMemberType": "Example Member",
"taxonomicRank": "Subfamily",
"scientificName": "",
"otherNames": [],
"wikipediaImg": "",
"wikipediaPage": "https://en.wikipedia.org/wiki/Echimyidae",
"popularAncestors": [
"rodent",
"mammal",
"animal",
"life"
],
"subtaxa": [
"armored rat",
"ferreira's spiny tree rat"
]
}