{
"description":"",
"popularity":10,
"extinct":true,
"name":"Falcarius",
"parentTaxon":"therizinosaur",
"popularSubtaxa":[],
"exampleMember":"",
"exampleMemberType":"",
"taxonomicRank":"Genus",
"scientificName":"",
"otherNames":[],
"wikipediaImg":"https://upload.wikimedia.org/wikipedia/commons/thumb/7/72/Falcarius_utahensis_DWER_500.JPG/330px-Falcarius_utahensis_DWER_500.JPG",
"wikipediaPage":"https://en.wikipedia.org/wiki/Falcarius",
"popularAncestors":[
"saurischia",
"dinosaur",
"animal",
"life"
],
"subtaxa":[],
"popularAncestorPops":[
40,
95,
95,
100
],
"popularSubtaxaPops":[],
"needs_wiki_img_checked":true
}