{
"description": "",
"popularity": "",
"extinct": false,
"name": "Glires",
"parentTaxon": "euarchontoglires",
"popularSubtaxa": [
"european rabbit",
"cottontail rabbit",
"rat"
],
"exampleMember": "zalambdalestes",
"exampleMemberType": "Early Member",
"taxonomicRank": "Unranked",
"scientificName": "",
"otherNames": [],
"wikipediaImg": "",
"wikipediaPage": "http://en.wikipedia.org/wiki/Glires",
"popularAncestors": [
"mammal",
"amniote",
"animal",
"life"
],
"subtaxa": [
"lagomorpha",
"rodent",
"zalambdalestes"
]
}