{
"description":"",
"popularity":75,
"extinct":false,
"name":"Hamster",
"parentTaxon":"cricetidae",
"popularSubtaxa":[],
"exampleMember":"",
"exampleMemberType":"",
"taxonomicRank":"Subfamily",
"scientificName":"Cricetinae",
"otherNames":[],
"wikipediaImg":"https://upload.wikimedia.org/wikipedia/commons/thumb/8/85/Syrian_hamster_filling_his_cheek_pouches_with_Dandelion_leaves.JPG/330px-Syrian_hamster_filling_his_cheek_pouches_with_Dandelion_leaves.JPG",
"wikipediaPage":"https://en.wikipedia.org/wiki/Hamster",
"popularAncestors":[
"rodent",
"mammal",
"animal",
"life"
],
"subtaxa":[],
"popularAncestorPops":[
70,
70,
95,
100
],
"popularSubtaxaPops":[]
}