{
"description":"",
"popularity":"",
"extinct":false,
"name":"Iguania",
"parentTaxon":"toxicofera subclade 1",
"popularSubtaxa":[
"iguana",
"chinese water dragon",
"australian water dragon"
],
"exampleMember":"chinese water dragon",
"exampleMemberType":"Example Member",
"taxonomicRank":"Suborder",
"scientificName":"",
"otherNames":[],
"wikipediaImg":"",
"wikipediaPage":"https://en.wikipedia.org/wiki/Iguania",
"popularAncestors":[
"amniote",
"tetrapod",
"animal",
"life"
],
"subtaxa":[
"acrodonta",
"iguanoidea"
],
"popularAncestorPops":[
50,
50,
95,
100
],
"popularSubtaxaPops":[
55,
60,
55
]
}