{
"description":"",
"popularity":"",
"extinct":false,
"name":"Magnoliales subclade 1",
"parentTaxon":"magnoliales",
"popularSubtaxa":[
"magnolia",
"eupomatia",
"tulip tree"
],
"exampleMember":"galbulimima",
"exampleMemberType":"Example Member",
"taxonomicRank":"Unnamed Clade",
"scientificName":"",
"otherNames":[],
"wikipediaImg":"",
"wikipediaPage":"https://en.wikipedia.org/wiki/Magnoliales",
"popularAncestors":[
"flowering plant",
"land plant",
"cellular life",
"life"
],
"subtaxa":[
"magnoliaceae",
"magnoliales subclade 2"
],
"popularAncestorPops":[
40,
95,
50,
100
],
"popularSubtaxaPops":[
55,
60,
40
]
}