{
"description":"",
"popularity":10,
"extinct":true,
"name":"Micropholis amphibian",
"parentTaxon":"amphibamidae",
"popularSubtaxa":[],
"exampleMember":"",
"exampleMemberType":"",
"taxonomicRank":"Genus",
"scientificName":"",
"otherNames":[],
"wikipediaImg":"https://upload.wikimedia.org/wikipedia/commons/thumb/b/b2/Micropholis_stowi.jpg/330px-Micropholis_stowi.jpg",
"wikipediaPage":"https://en.wikipedia.org/wiki/Micropholis_%28amphibian%29",
"popularAncestors":[
"amphibian",
"tetrapod",
"animal",
"life"
],
"subtaxa":[],
"popularAncestorPops":[
70,
50,
95,
100
],
"popularSubtaxaPops":[],
"needs_wiki_img_checked":true
}