{
"description":"",
"popularity":"",
"extinct":true,
"name":"Microraptoria subclade 2",
"parentTaxon":"microraptoria subclade 1",
"popularSubtaxa":[
"microraptor",
"graciliraptor",
"sinornithosaurus"
],
"exampleMember":"sinornithosaurus",
"exampleMemberType":"Example Member",
"taxonomicRank":"Unnamed Clade",
"scientificName":"",
"otherNames":[],
"wikipediaImg":"",
"wikipediaPage":"http://en.wikipedia.org/wiki/Microraptoria#Classification",
"popularAncestors":[
"saurischia",
"dinosaur",
"animal",
"life"
],
"subtaxa":[
"microraptor",
"sinornithosaurus",
"graciliraptor"
],
"popularAncestorPops":[
40,
95,
95,
100
],
"popularSubtaxaPops":[
50,
10,
10
],
"popularSubtaxaSameBranch":""
}