{
"description":"",
"popularity":"",
"extinct":false,
"name":"Neosuchia",
"parentTaxon":"metasuchia subclade 1",
"popularSubtaxa":[
"gharial",
"alligator",
"crocodile"
],
"exampleMember":"goniopholis",
"exampleMemberType":"Early Member",
"taxonomicRank":"Clade",
"scientificName":"",
"otherNames":[],
"wikipediaImg":"",
"wikipediaPage":"https://en.wikipedia.org/wiki/Neosuchia",
"popularAncestors":[
"amniote",
"tetrapod",
"animal",
"life"
],
"subtaxa":[
"goniopholis",
"neosuchia subclade 1"
],
"popularAncestorPops":[
50,
50,
95,
100
],
"popularSubtaxaPops":[
50,
85,
80
],
"needs_wiki_img_checked":true
}