{
"description":"",
"popularity":"",
"extinct":true,
"name":"Noasauridae",
"parentTaxon":"abelisaur",
"popularSubtaxa":[
"noasaurus",
"masiakasaurus",
"velocisaurus"
],
"exampleMember":"noasaurus",
"exampleMemberType":"Example Member",
"taxonomicRank":"Family",
"scientificName":"",
"otherNames":[],
"wikipediaImg":"",
"wikipediaPage":"",
"popularAncestors":[
"saurischia",
"dinosaur",
"animal",
"life"
],
"subtaxa":[
"noasaurus",
"masiakasaurus",
"velocisaurus"
],
"popularAncestorPops":[
40,
95,
95,
100
],
"popularSubtaxaPops":[
20,
10,
10
],
"popularSubtaxaSameBranch":""
}