{
"description":"",
"popularity":50,
"extinct":false,
"name":"Northern mole vole",
"parentTaxon":"arvicolinae",
"popularSubtaxa":[],
"exampleMember":"",
"exampleMemberType":"",
"taxonomicRank":"Species",
"scientificName":"Ellobius talpinus",
"otherNames":[],
"wikipediaImg":"https://upload.wikimedia.org/wikipedia/commons/thumb/2/2f/Ellobius_talpinus.jpg/330px-Ellobius_talpinus.jpg",
"wikipediaPage":"https://en.wikipedia.org/wiki/Northern_mole_vole",
"popularAncestors":[
"rodent",
"mammal",
"animal",
"life"
],
"subtaxa":[],
"popularAncestorPops":[
70,
70,
95,
100
],
"popularSubtaxaPops":[],
"popularSubtaxaSameBranch":""
}