{
"description":"",
"popularity":30,
"extinct":true,
"name":"Ophthalmosaurinae",
"parentTaxon":"ophthalmosauridae",
"popularSubtaxa":[
"ophthalmosaurus",
"acamptonectes"
],
"exampleMember":"",
"exampleMemberType":"",
"taxonomicRank":"Subfamily",
"scientificName":"",
"otherNames":[],
"wikipediaImg":"https://upload.wikimedia.org/wikipedia/commons/thumb/2/2d/Ophthalmosaurus_BW.jpg/220px-Ophthalmosaurus_BW.jpg",
"wikipediaPage":"https://en.wikipedia.org/wiki/Ophthalmosaurus",
"popularAncestors":[
"ichthyosaur",
"amniote",
"animal",
"life"
],
"subtaxa":[
"acamptonectes",
"ophthalmosaurus"
],
"popularAncestorPops":[
50,
50,
95,
100
],
"popularSubtaxaPops":[
10,
10
],
"needs_wiki_img_checked":true
}