{
"description": "",
"popularity": "",
"extinct": true,
"name": "Ornithomimosauria subclade 4",
"parentTaxon": "ornithomimosauria subclade 3",
"popularSubtaxa": [
"deinocheirus",
"gallimimus",
"ornithomimus"
],
"exampleMember": "beishanlong",
"exampleMemberType": "Example Member",
"taxonomicRank": "Unnamed Clade",
"scientificName": "",
"otherNames": [],
"wikipediaImg": "",
"wikipediaPage": "https://en.wikipedia.org/wiki/Ornithomimosauria",
"popularAncestors": [
"saurischia",
"dinosaur",
"animal",
"life"
],
"subtaxa": [
"deinocheiridae",
"ornithomimidae"
],
"popularAncestorPops": [
40,
95,
95,
100
]
}