{
"description":"",
"popularity":"",
"extinct":true,
"name":"Oviraptoridae subclade 3",
"parentTaxon":"oviraptoridae subclade 2",
"popularSubtaxa":[
"rinchenia",
"citipati"
],
"exampleMember":"rinchenia",
"exampleMemberType":"Example Member",
"taxonomicRank":"Unnamed Clade",
"scientificName":"",
"otherNames":[],
"wikipediaImg":"",
"wikipediaPage":"https://en.wikipedia.org/wiki/Oviraptoridae",
"popularAncestors":[
"saurischia",
"dinosaur",
"animal",
"life"
],
"subtaxa":[
"citipati",
"rinchenia"
],
"popularAncestorPops":[
40,
95,
95,
100
],
"popularSubtaxaPops":[
10,
10
]
}