{
"description":"",
"popularity":"",
"extinct":true,
"name":"Phytosauridae subclade 1",
"parentTaxon":"phytosauridae",
"popularSubtaxa":[
"machaeroprosopus",
"mystriosuchus",
"protome"
],
"exampleMember":"rutiodon",
"exampleMemberType":"Example Member",
"taxonomicRank":"Unnamed Clade",
"scientificName":"",
"otherNames":[],
"wikipediaImg":"",
"wikipediaPage":"https://en.wikipedia.org/wiki/Phytosaur",
"popularAncestors":[
"amniote",
"tetrapod",
"animal",
"life"
],
"subtaxa":[
"leptosuchomorpha",
"machaeroprosopus",
"protome",
"rutiodon"
],
"popularAncestorPops":[
50,
50,
95,
100
],
"popularSubtaxaPops":[
10,
10,
10
],
"popularSubtaxaSameBranch":"",
"additionalSubTaxa":[]
}