{
"description":"",
"popularity":"",
"extinct":false,
"name":"Procyon",
"parentTaxon":"procyonidae subclade 2",
"popularSubtaxa":[
"crab-eating raccoon",
"cozumel raccoon",
"raccoon"
],
"exampleMember":"raccoon",
"exampleMemberType":"Example Member",
"taxonomicRank":"Genus",
"scientificName":"",
"otherNames":[],
"wikipediaImg":"",
"wikipediaPage":"http://en.wikipedia.org/wiki/Procyon_%28genus%29",
"popularAncestors":[
"caniformia",
"carnivora",
"animal",
"life"
],
"subtaxa":[
"cozumel raccoon",
"crab-eating raccoon",
"raccoon"
],
"popularAncestorPops":[
50,
60,
95,
100
],
"popularSubtaxaPops":[
30,
30,
70
]
}