{
"description":"",
"popularity":"",
"extinct":false,
"name":"Reptiliomorpha",
"parentTaxon":"tetrapod",
"popularSubtaxa":[
"human",
"dinosaur",
"bird"
],
"exampleMember":"eoherpeton",
"exampleMemberType":"Early Member",
"taxonomicRank":"Clade",
"scientificName":"",
"otherNames":[],
"wikipediaImg":"",
"wikipediaPage":"http://en.wikipedia.org/wiki/Reptiliomorpha",
"popularAncestors":[
"tetrapod",
"bony fish",
"animal",
"life"
],
"subtaxa":[
"amniote",
"embolomeri"
],
"popularAncestorPops":[
50,
60,
95,
100
],
"popularSubtaxaPops":[
100,
95,
95
],
"needs_wiki_img_checked":true
}