{
"description": "",
"popularity": 50,
"extinct": false,
"name": "Rock cavy",
"parentTaxon": "hydrochoerinae",
"popularSubtaxa": [],
"exampleMember": "",
"exampleMemberType": "",
"taxonomicRank": "Species",
"scientificName": "Kerodon rupestris",
"otherNames": [
"moc\u00c3\u00b3"
],
"wikipediaImg": "https://upload.wikimedia.org/wikipedia/commons/thumb/6/6c/Kerodon_rupestris.jpg/220px-Kerodon_rupestris.jpg",
"wikipediaPage": "https://en.wikipedia.org/wiki/Rock_cavy",
"popularAncestors": [
"rodent",
"mammal",
"animal",
"life"
],
"subtaxa": []
}