{
"description":"",
"popularity":55,
"extinct":false,
"name":"Silverfish",
"parentTaxon":"lepismatidae",
"exampleMember":"",
"exampleMemberType":"",
"taxonomicRank":"Species",
"scientificName":"Lepisma saccharinum",
"otherNames":[],
"wikipediaImg":"https://upload.wikimedia.org/wikipedia/commons/thumb/8/84/LepismaSaccharina.jpg/330px-LepismaSaccharina.jpg",
"wikipediaPage":"https://en.wikipedia.org/wiki/Silverfish",
"subtaxa":[],
"popularAncestors":[
"insect",
"arthropod",
"animal",
"life"
],
"popularAncestorPops":[
95,
50,
95,
100
],
"popularSubtaxa":[],
"popularSubtaxaPops":[],
"popularSubtaxaSameBranch":""
}