{
"description":"",
"popularity":"",
"extinct":false,
"name":"Spalacidae",
"parentTaxon":"muroidea",
"popularSubtaxa":[
"blind mole rats",
"bamboo rat",
"zokor"
],
"exampleMember":"zokor",
"exampleMemberType":"Example Member",
"taxonomicRank":"Family",
"scientificName":"",
"otherNames":[],
"wikipediaImg":"",
"wikipediaPage":"https://en.wikipedia.org/wiki/Spalacidae",
"popularAncestors":[
"rodent",
"mammal",
"animal",
"life"
],
"subtaxa":[
"blind mole rats",
"rhizomyinae",
"zokor"
],
"popularAncestorPops":[
70,
70,
95,
100
],
"popularSubtaxaPops":[
50,
50,
50
],
"needs_wiki_img_checked":true
}