{
"description":"",
"popularity":"",
"extinct":true,
"name":"Suchia subclade 1",
"parentTaxon":"suchia",
"popularSubtaxa":[
"aetosaurus",
"typothorax",
"revueltosaurus"
],
"exampleMember":"revueltosaurus",
"exampleMemberType":"Example Member",
"taxonomicRank":"Unnamed Clade",
"scientificName":"",
"otherNames":[],
"wikipediaImg":"",
"wikipediaPage":"https://en.wikipedia.org/wiki/Suchia",
"popularAncestors":[
"amniote",
"tetrapod",
"animal",
"life"
],
"subtaxa":[
"aetosaur",
"revueltosaurus"
],
"popularAncestorPops":[
50,
50,
95,
100
],
"popularSubtaxaPops":[
20,
20,
10
],
"popularSubtaxaSameBranch":"0,1"
}