{
"description":"",
"popularity":"",
"extinct":false,
"name":"Testudinata",
"parentTaxon":"pantestudines subclade 3",
"popularSubtaxa":[
"turtle",
"kayentachelys",
"proganochelys"
],
"exampleMember":"proganochelys",
"exampleMemberType":"Early Member",
"taxonomicRank":"Clade",
"scientificName":"",
"otherNames":[],
"wikipediaImg":"",
"wikipediaPage":"https://en.wikipedia.org/wiki/Testudinata",
"popularAncestors":[
"amniote",
"tetrapod",
"animal",
"life"
],
"subtaxa":[
"testudinata subclade 1",
"proganochelys"
],
"popularAncestorPops":[
50,
50,
95,
100
],
"popularSubtaxaPops":[
80,
10,
10
],
"popularSubtaxaSameBranch":"0,1",
"additionalSubTaxa":[]
}