{
"description":"",
"popularity":"",
"extinct":false,
"name":"Theropoda subclade 1",
"parentTaxon":"theropoda",
"popularSubtaxa":[
"bird",
"dilophosaurus",
"spinosaurus"
],
"exampleMember":"eoraptor",
"exampleMemberType":"Early Member",
"taxonomicRank":"Unnamed Clade",
"scientificName":"",
"otherNames":[],
"wikipediaImg":"",
"wikipediaPage":"https://en.wikipedia.org/wiki/Theropoda",
"popularAncestors":[
"saurischia",
"dinosaur",
"animal",
"life"
],
"subtaxa":[
"theropoda subclade 2",
"eoraptor"
],
"popularAncestorPops":[
40,
95,
95,
100
],
"popularSubtaxaPops":[
95,
60,
60
],
"popularSubtaxaSameBranch":"0,2",
"additionalSubTaxa":[]
}