{
"description":"",
"popularity":50,
"extinct":false,
"name":"Trithuria",
"parentTaxon":"nymphaeales",
"popularSubtaxa":[],
"exampleMember":"",
"exampleMemberType":"",
"taxonomicRank":"Genus",
"scientificName":"",
"otherNames":[],
"wikipediaImg":"https://upload.wikimedia.org/wikipedia/en/thumb/6/6c/Trithuria_inconspicua_lake.jpg/330px-Trithuria_inconspicua_lake.jpg",
"wikipediaPage":"https://en.wikipedia.org/wiki/Trithuria",
"popularAncestors":[
"flowering plant",
"land plant",
"cellular life",
"life"
],
"subtaxa":[],
"popularAncestorPops":[
40,
95,
50,
100
],
"popularSubtaxaPops":[],
"popularSubtaxaSameBranch":""
}